quaterion_models/__init__.py
quaterion_models/encoders/__init__.py
quaterion_models/encoders/encoder.py
quaterion_models/encoders/extras/__init__.py
quaterion_models/encoders/extras/fasttext_encoder.py
quaterion_models/encoders/switch_encoder.py
quaterion_models/heads/__init__.py
quaterion_models/heads/empty_head.py
quaterion_models/heads/encoder_head.py
quaterion_models/heads/gated_head.py
quaterion_models/heads/sequential_head.py
quaterion_models/heads/skip_connection_head.py
quaterion_models/heads/softmax_head.py
quaterion_models/heads/stacked_projection_head.py
quaterion_models/heads/switch_head.py
quaterion_models/heads/widening_head.py
quaterion_models/model.py
quaterion_models/modules/__init__.py
quaterion_models/modules/simple.py
quaterion_models/types/__init__.py
quaterion_models/utils/__init__.py
quaterion_models/utils/classes.py
quaterion_models/utils/meta.py
quaterion_models/utils/tensors.py
quaterion_models-0.1.19.dist-info/LICENSE
quaterion_models-0.1.19.dist-info/WHEEL
quaterion_models-0.1.19.dist-info/METADATA
quaterion_models-0.1.19.dist-info/RECORD
