Metadata-Version: 2.1
Name: quaterion-models
Version: 0.1.19
Summary: The collection of building blocks to build fine-tunable similarity learning models
Home-page: https://github.com/qdrant/quaterion-models
Keywords: framework,metric-learning,similarity,similarity-learning,deep-learning,pytorch
Author: Quaterion Authors
Author-email: team@qdrant.tech
Requires-Python: >=3.8,<3.11
Classifier: Programming Language :: Python :: 3
Classifier: Programming Language :: Python :: 3.8
Classifier: Programming Language :: Python :: 3.9
Classifier: Programming Language :: Python :: 3.10
Provides-Extra: fasttext
Requires-Dist: gensim (>=4.1.2,<5.0.0); extra == "fasttext"
Requires-Dist: numpy (>=1.22,<2.0)
Requires-Dist: torch (>=1.8.2)
Project-URL: Repository, https://github.com/qdrant/quaterion-models
